tests/__init__.py
tests/test_fft.py
tests/test_template.py
zfinder/__init__.py
zfinder/fft.py
zfinder/finder.py
zfinder/fits2flux.py
zfinder/flux.py
zfinder/plotter.py
zfinder/run.py
zfinder/template.py
zfinder/uncertainty.py
zfinder/utils.py
zfinder/zfind.py
zfinder/zfind_template.py
zfinder-1.0.2.dist-info/LICENSE.txt
zfinder-1.0.2.dist-info/METADATA
zfinder-1.0.2.dist-info/WHEEL
zfinder-1.0.2.dist-info/top_level.txt
zfinder-1.0.2.dist-info/RECORD
