Metadata-Version: 2.1
Name: zfinder
Version: 1.0.2
Summary: Redshift finding algorithm
Author: Daniel Lyon
Author-email: daniellyon31@gmail.com
Keywords: python,visualisation,redshift,galaxy-evolution,cosmology,epoch-of-reionisation,radio-galaxies,active-galactic-nuclei,high-redshift,galaxies,black-holes
Classifier: Development Status :: 5 - Production/Stable
Classifier: Intended Audience :: Science/Research
Classifier: Programming Language :: Python :: 3
Classifier: Operating System :: Unix
Classifier: Operating System :: MacOS :: MacOS X
Classifier: Operating System :: Microsoft :: Windows
License-File: LICENSE.txt
Requires-Dist: numpy
Requires-Dist: matplotlib
Requires-Dist: scipy
Requires-Dist: astropy
Requires-Dist: photutils
Requires-Dist: PyAstronomy
Requires-Dist: sslf
Requires-Dist: radio-beam
Requires-Dist: tqdm
